cht_sfincs/__init__.py
cht_sfincs/boundary_conditions.py
cht_sfincs/cross_sections.py
cht_sfincs/grid.py
cht_sfincs/grid_v2.py
cht_sfincs/initial_conditions.py
cht_sfincs/input.py
cht_sfincs/mask.py
cht_sfincs/observation_points.py
cht_sfincs/point_sources.py
cht_sfincs/quadtree_grid.py
cht_sfincs/quadtree_grid_snapwave.py
cht_sfincs/regular_grid.py
cht_sfincs/sfincs.py
cht_sfincs/sfincs_builder.py
cht_sfincs/snapwave.py
cht_sfincs/subgrid.py
cht_sfincs/thin_dams.py
cht_sfincs/wave_makers.py
cht_sfincs/weirs.py
cht_sfincs/old_version/__init__.py
cht_sfincs/old_version/quadtree.py
cht_sfincs/old_version/regulargrid.py
cht_sfincs/old_version/sfincs.py
cht_sfincs/old_version/sfincs_builder.py
cht_sfincs/old_version/subgrid.py
cht_sfincs-1.0.0.dist-info/LICENSE
cht_sfincs-1.0.0.dist-info/METADATA
cht_sfincs-1.0.0.dist-info/WHEEL
cht_sfincs-1.0.0.dist-info/top_level.txt
cht_sfincs-1.0.0.dist-info/RECORD
